{"test":{"id":846275576,"classId":-206442501,"package":"io.harness.service.instancesynchandler","class":"K8sInstanceSyncHandlerTest","method":"testGetDeploymentInfo","params":"()"},"source":{"id":-253831166,"classId":1909834988,"package":"io.harness.delegate.beans.instancesync.info","class":"K8sServerInstanceInfo","method":"build","params":"()"}}
{"test":{"id":1390315293,"classId":-206442501,"package":"io.harness.service.instancesynchandler","class":"K8sInstanceSyncHandlerTest","method":"testGetInstanceInfoForServerInstance","params":"()"},"source":{"id":2059924819,"classId":1909834988,"package":"io.harness.delegate.beans.instancesync.info","class":"K8sServerInstanceInfo","method":"getName","params":"()"}}
{"test":{"id":1390315293,"classId":-206442501,"package":"io.harness.service.instancesynchandler","class":"K8sInstanceSyncHandlerTest","method":"testGetInstanceInfoForServerInstance","params":"()"},"source":{"id":693846688,"classId":-1297480033,"package":"io.harness.dtos.instanceinfo","class":"K8sInstanceInfoDTO","method":"builder","params":"()"}}
{"test":{"id":846275576,"classId":-206442501,"package":"io.harness.service.instancesynchandler","class":"K8sInstanceSyncHandlerTest","method":"testGetDeploymentInfo","params":"()"},"source":{"id":539391005,"classId":1536503721,"package":"io.harness.service.instancesynchandler","class":"K8sInstanceSyncHandler","method":"getNamespaces","params":"(java.util.List)"}}
{"test":{"id":1390315293,"classId":-206442501,"package":"io.harness.service.instancesynchandler","class":"K8sInstanceSyncHandlerTest","method":"testGetInstanceInfoForServerInstance","params":"()"},"source":{"id":1137151227,"classId":192269376,"package":"io.harness.k8s.model","class":"K8sContainer","method":"","params":"(java.lang.String,java.lang.String,java.lang.String)"}}
{"test":{"id":1390315293,"classId":-206442501,"package":"io.harness.service.instancesynchandler","class":"K8sInstanceSyncHandlerTest","method":"testGetInstanceInfoForServerInstance","params":"()"},"source":{"id":833821109,"classId":-1297480033,"package":"io.harness.dtos.instanceinfo","class":"K8sInstanceInfoDTO","method":"build","params":"()"}}
{"test":{"id":1390315293,"classId":-206442501,"package":"io.harness.service.instancesynchandler","class":"K8sInstanceSyncHandlerTest","method":"testGetInstanceInfoForServerInstance","params":"()"},"source":{"id":1504598196,"classId":192269376,"package":"io.harness.k8s.model","class":"K8sContainer","method":"image","params":"(java.lang.String)"}}
{"test":{"id":846275576,"classId":-206442501,"package":"io.harness.service.instancesynchandler","class":"K8sInstanceSyncHandlerTest","method":"testGetDeploymentInfo","params":"()"},"source":{"id":776373858,"classId":-1445611270,"package":"io.harness.cdng.infra.beans","class":"InfrastructureOutcomeAbstract","method":"","params":"()"}}
{"test":{"id":1390315293,"classId":-206442501,"package":"io.harness.service.instancesynchandler","class":"K8sInstanceSyncHandlerTest","method":"testGetInstanceInfoForServerInstance","params":"()"},"source":{"id":-1971396778,"classId":192269376,"package":"io.harness.k8s.model","class":"K8sContainer","method":"build","params":"()"}}
{"test":{"id":1390315293,"classId":-206442501,"package":"io.harness.service.instancesynchandler","class":"K8sInstanceSyncHandlerTest","method":"testGetInstanceInfoForServerInstance","params":"()"},"source":{"id":4130854,"classId":-1297480033,"package":"io.harness.dtos.instanceinfo","class":"K8sInstanceInfoDTO","method":"podIP","params":"(java.lang.String)"}}
{"test":{"id":-664095006,"classId":-206442501,"package":"io.harness.service.instancesynchandler","class":"K8sInstanceSyncHandlerTest","method":"testGetInfrastructureMappingType","params":"()"},"source":{"id":-1740207780,"classId":1536503721,"package":"io.harness.service.instancesynchandler","class":"K8sInstanceSyncHandler","method":"getInfrastructureKind","params":"()"}}
{"test":{"id":1390315293,"classId":-206442501,"package":"io.harness.service.instancesynchandler","class":"K8sInstanceSyncHandlerTest","method":"testGetInstanceInfoForServerInstance","params":"()"},"source":{"id":-80388768,"classId":1909834988,"package":"io.harness.delegate.beans.instancesync.info","class":"K8sServerInstanceInfo","method":"namespace","params":"(java.lang.String)"}}
{"test":{"id":1390315293,"classId":-206442501,"package":"io.harness.service.instancesynchandler","class":"K8sInstanceSyncHandlerTest","method":"testGetInstanceInfoForServerInstance","params":"()"},"source":{"id":1938844751,"classId":1536503721,"package":"io.harness.service.instancesynchandler","class":"K8sInstanceSyncHandler","method":"getInstanceInfoForServerInstance","params":"(io.harness.delegate.beans.instancesync.ServerInstanceInfo)"}}
{"test":{"id":846275576,"classId":-206442501,"package":"io.harness.service.instancesynchandler","class":"K8sInstanceSyncHandlerTest","method":"testGetDeploymentInfo","params":"()"},"source":{"id":1517365623,"classId":1909834988,"package":"io.harness.delegate.beans.instancesync.info","class":"K8sServerInstanceInfo","method":"","params":"(java.lang.String,java.lang.String,java.lang.String,java.lang.String,java.lang.String,java.util.List)"}}
{"test":{"id":1390315293,"classId":-206442501,"package":"io.harness.service.instancesynchandler","class":"K8sInstanceSyncHandlerTest","method":"testGetInstanceInfoForServerInstance","params":"()"},"source":{"id":342359207,"classId":192269376,"package":"io.harness.k8s.model","class":"K8sContainer","method":"getName","params":"()"}}
{"test":{"id":846275576,"classId":-206442501,"package":"io.harness.service.instancesynchandler","class":"K8sInstanceSyncHandlerTest","method":"testGetDeploymentInfo","params":"()"},"source":{"id":-1050787760,"classId":-1684552961,"package":"io.harness.dtos.deploymentinfo","class":"K8sDeploymentInfoDTO","method":"","params":"(java.util.LinkedHashSet,java.lang.String,java.lang.String)"}}
{"test":{"id":1390315293,"classId":-206442501,"package":"io.harness.service.instancesynchandler","class":"K8sInstanceSyncHandlerTest","method":"testGetInstanceInfoForServerInstance","params":"()"},"source":{"id":-1632682006,"classId":-1297480033,"package":"io.harness.dtos.instanceinfo","class":"K8sInstanceInfoDTO","method":"podName","params":"(java.lang.String)"}}
{"test":{"id":1390315293,"classId":-206442501,"package":"io.harness.service.instancesynchandler","class":"K8sInstanceSyncHandlerTest","method":"testGetInstanceInfoForServerInstance","params":"()"},"source":{"id":1116944317,"classId":-1297480033,"package":"io.harness.dtos.instanceinfo","class":"K8sInstanceInfoDTO","method":"getPodIP","params":"()"}}
{"test":{"id":846275576,"classId":-206442501,"package":"io.harness.service.instancesynchandler","class":"K8sInstanceSyncHandlerTest","method":"testGetDeploymentInfo","params":"()"},"source":{"id":743823287,"classId":1909834988,"package":"io.harness.delegate.beans.instancesync.info","class":"K8sServerInstanceInfo","method":"getNamespace","params":"()"}}
{"test":{"id":1390315293,"classId":-206442501,"package":"io.harness.service.instancesynchandler","class":"K8sInstanceSyncHandlerTest","method":"testGetInstanceInfoForServerInstance","params":"()"},"source":{"id":-1186970759,"classId":1909834988,"package":"io.harness.delegate.beans.instancesync.info","class":"K8sServerInstanceInfo","method":"releaseName","params":"(java.lang.String)"}}
{"test":{"id":1390315293,"classId":-206442501,"package":"io.harness.service.instancesynchandler","class":"K8sInstanceSyncHandlerTest","method":"testGetInstanceInfoForServerInstance","params":"()"},"source":{"id":-1552722051,"classId":520260117,"package":"io.harness.dtos.instanceinfo","class":"InstanceInfoDTO","method":"","params":"()"}}
{"test":{"id":1390315293,"classId":-206442501,"package":"io.harness.service.instancesynchandler","class":"K8sInstanceSyncHandlerTest","method":"testGetInstanceInfoForServerInstance","params":"()"},"source":{"id":705960302,"classId":192269376,"package":"io.harness.k8s.model","class":"K8sContainer","method":"getContainerId","params":"()"}}
{"test":{"id":1390315293,"classId":-206442501,"package":"io.harness.service.instancesynchandler","class":"K8sInstanceSyncHandlerTest","method":"testGetInstanceInfoForServerInstance","params":"()"},"source":{"id":1714206757,"classId":-206442501,"package":"io.harness.service.instancesynchandler","class":"K8sInstanceSyncHandlerTest","method":"getK8sContainer","params":"(java.lang.String,java.lang.String,java.lang.String)"}}
{"test":{"id":1390315293,"classId":-206442501,"package":"io.harness.service.instancesynchandler","class":"K8sInstanceSyncHandlerTest","method":"testGetInstanceInfoForServerInstance","params":"()"},"source":{"id":-393805587,"classId":1909834988,"package":"io.harness.delegate.beans.instancesync.info","class":"K8sServerInstanceInfo","method":"builder","params":"()"}}
{"test":{"id":846275576,"classId":-206442501,"package":"io.harness.service.instancesynchandler","class":"K8sInstanceSyncHandlerTest","method":"testGetDeploymentInfo","params":"()"},"source":{"id":-80388768,"classId":1909834988,"package":"io.harness.delegate.beans.instancesync.info","class":"K8sServerInstanceInfo","method":"namespace","params":"(java.lang.String)"}}
{"test":{"id":1390315293,"classId":-206442501,"package":"io.harness.service.instancesynchandler","class":"K8sInstanceSyncHandlerTest","method":"testGetInstanceInfoForServerInstance","params":"()"},"source":{"id":-1686214645,"classId":192269376,"package":"io.harness.k8s.model","class":"K8sContainer","method":"getImage","params":"()"}}
{"test":{"id":1390315293,"classId":-206442501,"package":"io.harness.service.instancesynchandler","class":"K8sInstanceSyncHandlerTest","method":"testGetInstanceInfoForServerInstance","params":"()"},"source":{"id":-1008887973,"classId":1909834988,"package":"io.harness.delegate.beans.instancesync.info","class":"K8sServerInstanceInfo","method":"getContainerList","params":"()"}}
{"test":{"id":846275576,"classId":-206442501,"package":"io.harness.service.instancesynchandler","class":"K8sInstanceSyncHandlerTest","method":"testGetDeploymentInfo","params":"()"},"source":{"id":-1795638264,"classId":-1684552961,"package":"io.harness.dtos.deploymentinfo","class":"K8sDeploymentInfoDTO","method":"blueGreenStageColor","params":"(java.lang.String)"}}
{"test":{"id":1390315293,"classId":-206442501,"package":"io.harness.service.instancesynchandler","class":"K8sInstanceSyncHandlerTest","method":"testGetInstanceInfoForServerInstance","params":"()"},"source":{"id":1517365623,"classId":1909834988,"package":"io.harness.delegate.beans.instancesync.info","class":"K8sServerInstanceInfo","method":"","params":"(java.lang.String,java.lang.String,java.lang.String,java.lang.String,java.lang.String,java.util.List)"}}
{"test":{"id":846275576,"classId":-206442501,"package":"io.harness.service.instancesynchandler","class":"K8sInstanceSyncHandlerTest","method":"testGetDeploymentInfo","params":"()"},"source":{"id":-869460550,"classId":1536503721,"package":"io.harness.service.instancesynchandler","class":"K8sInstanceSyncHandler","method":"getDeploymentInfo","params":"(io.harness.cdng.infra.beans.InfrastructureOutcome,java.util.List)"}}
{"test":{"id":846275576,"classId":-206442501,"package":"io.harness.service.instancesynchandler","class":"K8sInstanceSyncHandlerTest","method":"testGetDeploymentInfo","params":"()"},"source":{"id":446748181,"classId":-1684552961,"package":"io.harness.dtos.deploymentinfo","class":"K8sDeploymentInfoDTO","method":"build","params":"()"}}
{"test":{"id":1390315293,"classId":-206442501,"package":"io.harness.service.instancesynchandler","class":"K8sInstanceSyncHandlerTest","method":"testGetInstanceInfoForServerInstance","params":"()"},"source":{"id":924505095,"classId":-1297480033,"package":"io.harness.dtos.instanceinfo","class":"K8sInstanceInfoDTO","method":"","params":"()"}}
{"test":{"id":1390315293,"classId":-206442501,"package":"io.harness.service.instancesynchandler","class":"K8sInstanceSyncHandlerTest","method":"testGetInstanceInfoForServerInstance","params":"()"},"source":{"id":1169801834,"classId":-206442501,"package":"io.harness.service.instancesynchandler","class":"K8sInstanceSyncHandlerTest","method":"getContainerList","params":"()"}}
{"test":{"id":1390315293,"classId":-206442501,"package":"io.harness.service.instancesynchandler","class":"K8sInstanceSyncHandlerTest","method":"testGetInstanceInfoForServerInstance","params":"()"},"source":{"id":-1689949398,"classId":-1297480033,"package":"io.harness.dtos.instanceinfo","class":"K8sInstanceInfoDTO","method":"","params":"(java.lang.String,java.lang.String,java.lang.String,java.lang.String,java.lang.String,java.util.List)"}}
{"test":{"id":1390315293,"classId":-206442501,"package":"io.harness.service.instancesynchandler","class":"K8sInstanceSyncHandlerTest","method":"testGetInstanceInfoForServerInstance","params":"()"},"source":{"id":1293355092,"classId":-1297480033,"package":"io.harness.dtos.instanceinfo","class":"K8sInstanceInfoDTO","method":"blueGreenColor","params":"(java.lang.String)"}}
{"test":{"id":846275576,"classId":-206442501,"package":"io.harness.service.instancesynchandler","class":"K8sInstanceSyncHandlerTest","method":"testGetDeploymentInfo","params":"()"},"source":{"id":-175785174,"classId":2127855401,"package":"io.harness.cdng.infra.beans","class":"K8sDirectInfrastructureOutcome","method":"builder","params":"()"}}
{"test":{"id":846275576,"classId":-206442501,"package":"io.harness.service.instancesynchandler","class":"K8sInstanceSyncHandlerTest","method":"testGetDeploymentInfo","params":"()"},"source":{"id":-393805587,"classId":1909834988,"package":"io.harness.delegate.beans.instancesync.info","class":"K8sServerInstanceInfo","method":"builder","params":"()"}}
{"test":{"id":1390315293,"classId":-206442501,"package":"io.harness.service.instancesynchandler","class":"K8sInstanceSyncHandlerTest","method":"testGetInstanceInfoForServerInstance","params":"()"},"source":{"id":-99318484,"classId":-1297480033,"package":"io.harness.dtos.instanceinfo","class":"K8sInstanceInfoDTO","method":"releaseName","params":"(java.lang.String)"}}
{"test":{"id":1390315293,"classId":-206442501,"package":"io.harness.service.instancesynchandler","class":"K8sInstanceSyncHandlerTest","method":"testGetInstanceInfoForServerInstance","params":"()"},"source":{"id":-1694549506,"classId":378432662,"package":"io.harness.delegate.beans.instancesync","class":"ServerInstanceInfo","method":"","params":"()"}}
{"test":{"id":1390315293,"classId":-206442501,"package":"io.harness.service.instancesynchandler","class":"K8sInstanceSyncHandlerTest","method":"testGetInstanceInfoForServerInstance","params":"()"},"source":{"id":743823287,"classId":1909834988,"package":"io.harness.delegate.beans.instancesync.info","class":"K8sServerInstanceInfo","method":"getNamespace","params":"()"}}
{"test":{"id":1390315293,"classId":-206442501,"package":"io.harness.service.instancesynchandler","class":"K8sInstanceSyncHandlerTest","method":"testGetInstanceInfoForServerInstance","params":"()"},"source":{"id":1007263507,"classId":-1297480033,"package":"io.harness.dtos.instanceinfo","class":"K8sInstanceInfoDTO","method":"namespace","params":"(java.lang.String)"}}
{"test":{"id":846275576,"classId":-206442501,"package":"io.harness.service.instancesynchandler","class":"K8sInstanceSyncHandlerTest","method":"testGetDeploymentInfo","params":"()"},"source":{"id":608850386,"classId":-206442501,"package":"io.harness.service.instancesynchandler","class":"K8sInstanceSyncHandlerTest","method":"getServiceInstanceInfos","params":"()"}}
{"test":{"id":1390315293,"classId":-206442501,"package":"io.harness.service.instancesynchandler","class":"K8sInstanceSyncHandlerTest","method":"testGetInstanceInfoForServerInstance","params":"()"},"source":{"id":-1897865449,"classId":-1297480033,"package":"io.harness.dtos.instanceinfo","class":"K8sInstanceInfoDTO","method":"getBlueGreenColor","params":"()"}}
{"test":{"id":1390315293,"classId":-206442501,"package":"io.harness.service.instancesynchandler","class":"K8sInstanceSyncHandlerTest","method":"testGetInstanceInfoForServerInstance","params":"()"},"source":{"id":-1882221936,"classId":1909834988,"package":"io.harness.delegate.beans.instancesync.info","class":"K8sServerInstanceInfo","method":"getReleaseName","params":"()"}}
{"test":{"id":1390315293,"classId":-206442501,"package":"io.harness.service.instancesynchandler","class":"K8sInstanceSyncHandlerTest","method":"testGetInstanceInfoForServerInstance","params":"()"},"source":{"id":1309449572,"classId":1909834988,"package":"io.harness.delegate.beans.instancesync.info","class":"K8sServerInstanceInfo","method":"getBlueGreenColor","params":"()"}}
{"test":{"id":1390315293,"classId":-206442501,"package":"io.harness.service.instancesynchandler","class":"K8sInstanceSyncHandlerTest","method":"testGetInstanceInfoForServerInstance","params":"()"},"source":{"id":-93715230,"classId":-1297480033,"package":"io.harness.dtos.instanceinfo","class":"K8sInstanceInfoDTO","method":"containerList","params":"(java.util.List)"}}
{"test":{"id":846275576,"classId":-206442501,"package":"io.harness.service.instancesynchandler","class":"K8sInstanceSyncHandlerTest","method":"testGetDeploymentInfo","params":"()"},"source":{"id":-976911856,"classId":1909834988,"package":"io.harness.delegate.beans.instancesync.info","class":"K8sServerInstanceInfo","method":"name","params":"(java.lang.String)"}}
{"test":{"id":925410522,"classId":-206442501,"package":"io.harness.service.instancesynchandler","class":"K8sInstanceSyncHandlerTest","method":"testGetPerpetualTaskType","params":"()"},"source":{"id":-995792362,"classId":1536503721,"package":"io.harness.service.instancesynchandler","class":"K8sInstanceSyncHandler","method":"getPerpetualTaskType","params":"()"}}
{"test":{"id":846275576,"classId":-206442501,"package":"io.harness.service.instancesynchandler","class":"K8sInstanceSyncHandlerTest","method":"testGetDeploymentInfo","params":"()"},"source":{"id":-163147180,"classId":1909834988,"package":"io.harness.delegate.beans.instancesync.info","class":"K8sServerInstanceInfo","method":"","params":"()"}}
{"test":{"id":1390315293,"classId":-206442501,"package":"io.harness.service.instancesynchandler","class":"K8sInstanceSyncHandlerTest","method":"testGetInstanceInfoForServerInstance","params":"()"},"source":{"id":78764302,"classId":-1297480033,"package":"io.harness.dtos.instanceinfo","class":"K8sInstanceInfoDTO","method":"getContainerList","params":"()"}}
{"test":{"id":846275576,"classId":-206442501,"package":"io.harness.service.instancesynchandler","class":"K8sInstanceSyncHandlerTest","method":"testGetDeploymentInfo","params":"()"},"source":{"id":-887352728,"classId":-1684552961,"package":"io.harness.dtos.deploymentinfo","class":"K8sDeploymentInfoDTO","method":"namespaces","params":"(java.util.LinkedHashSet)"}}
{"test":{"id":1390315293,"classId":-206442501,"package":"io.harness.service.instancesynchandler","class":"K8sInstanceSyncHandlerTest","method":"testGetInstanceInfoForServerInstance","params":"()"},"source":{"id":-193705427,"classId":192269376,"package":"io.harness.k8s.model","class":"K8sContainer","method":"canEqual","params":"(java.lang.Object)"}}
{"test":{"id":846275576,"classId":-206442501,"package":"io.harness.service.instancesynchandler","class":"K8sInstanceSyncHandlerTest","method":"testGetDeploymentInfo","params":"()"},"source":{"id":-1181642589,"classId":-1684552961,"package":"io.harness.dtos.deploymentinfo","class":"K8sDeploymentInfoDTO","method":"getReleaseName","params":"()"}}
{"test":{"id":724830717,"classId":-1497153642,"package":"io.harness","class":"CategoryTest"},"source":{"id":1794565376,"classId":-1185934349,"package":"io.harness.rule","class":"RepeatRule","method":"getRepetition","params":"()"}}
{"test":{"id":846275576,"classId":-206442501,"package":"io.harness.service.instancesynchandler","class":"K8sInstanceSyncHandlerTest","method":"testGetDeploymentInfo","params":"()"},"source":{"id":-35810753,"classId":2127855401,"package":"io.harness.cdng.infra.beans","class":"K8sDirectInfrastructureOutcome","method":"build","params":"()"}}
{"test":{"id":1390315293,"classId":-206442501,"package":"io.harness.service.instancesynchandler","class":"K8sInstanceSyncHandlerTest","method":"testGetInstanceInfoForServerInstance","params":"()"},"source":{"id":-1181367505,"classId":1909834988,"package":"io.harness.delegate.beans.instancesync.info","class":"K8sServerInstanceInfo","method":"containerList","params":"(java.util.List)"}}
{"test":{"id":1390315293,"classId":-206442501,"package":"io.harness.service.instancesynchandler","class":"K8sInstanceSyncHandlerTest","method":"testGetInstanceInfoForServerInstance","params":"()"},"source":{"id":29292042,"classId":1909834988,"package":"io.harness.delegate.beans.instancesync.info","class":"K8sServerInstanceInfo","method":"getPodIP","params":"()"}}
{"test":{"id":846275576,"classId":-206442501,"package":"io.harness.service.instancesynchandler","class":"K8sInstanceSyncHandlerTest","method":"testGetDeploymentInfo","params":"()"},"source":{"id":-312835297,"classId":-1684552961,"package":"io.harness.dtos.deploymentinfo","class":"K8sDeploymentInfoDTO","method":"getBlueGreenStageColor","params":"()"}}
{"test":{"id":846275576,"classId":-206442501,"package":"io.harness.service.instancesynchandler","class":"K8sInstanceSyncHandlerTest","method":"testGetDeploymentInfo","params":"()"},"source":{"id":-1694549506,"classId":378432662,"package":"io.harness.delegate.beans.instancesync","class":"ServerInstanceInfo","method":"","params":"()"}}
{"test":{"id":846275576,"classId":-206442501,"package":"io.harness.service.instancesynchandler","class":"K8sInstanceSyncHandlerTest","method":"testGetDeploymentInfo","params":"()"},"source":{"id":-1083521421,"classId":1909834988,"package":"io.harness.delegate.beans.instancesync.info","class":"K8sServerInstanceInfo","method":"podIP","params":"(java.lang.String)"}}
{"test":{"id":846275576,"classId":-206442501,"package":"io.harness.service.instancesynchandler","class":"K8sInstanceSyncHandlerTest","method":"testGetDeploymentInfo","params":"()"},"source":{"id":205702817,"classId":1909834988,"package":"io.harness.delegate.beans.instancesync.info","class":"K8sServerInstanceInfo","method":"blueGreenColor","params":"(java.lang.String)"}}
{"test":{"id":1390315293,"classId":-206442501,"package":"io.harness.service.instancesynchandler","class":"K8sInstanceSyncHandlerTest","method":"testGetInstanceInfoForServerInstance","params":"()"},"source":{"id":-976911856,"classId":1909834988,"package":"io.harness.delegate.beans.instancesync.info","class":"K8sServerInstanceInfo","method":"name","params":"(java.lang.String)"}}
{"test":{"id":846275576,"classId":-206442501,"package":"io.harness.service.instancesynchandler","class":"K8sInstanceSyncHandlerTest","method":"testGetDeploymentInfo","params":"()"},"source":{"id":-137376675,"classId":1935605493,"package":"io.harness.dtos.deploymentinfo","class":"DeploymentInfoDTO","method":"","params":"()"}}
{"test":{"id":1390315293,"classId":-206442501,"package":"io.harness.service.instancesynchandler","class":"K8sInstanceSyncHandlerTest","method":"testGetInstanceInfoForServerInstance","params":"()"},"source":{"id":-1083521421,"classId":1909834988,"package":"io.harness.delegate.beans.instancesync.info","class":"K8sServerInstanceInfo","method":"podIP","params":"(java.lang.String)"}}
{"test":{"id":846275576,"classId":-206442501,"package":"io.harness.service.instancesynchandler","class":"K8sInstanceSyncHandlerTest","method":"testGetDeploymentInfo","params":"()"},"source":{"id":54873233,"classId":2127855401,"package":"io.harness.cdng.infra.beans","class":"K8sDirectInfrastructureOutcome","method":"","params":"()"}}
{"test":{"id":1390315293,"classId":-206442501,"package":"io.harness.service.instancesynchandler","class":"K8sInstanceSyncHandlerTest","method":"testGetInstanceInfoForServerInstance","params":"()"},"source":{"id":1393870999,"classId":192269376,"package":"io.harness.k8s.model","class":"K8sContainer","method":"containerId","params":"(java.lang.String)"}}
{"test":{"id":846275576,"classId":-206442501,"package":"io.harness.service.instancesynchandler","class":"K8sInstanceSyncHandlerTest","method":"testGetDeploymentInfo","params":"()"},"source":{"id":-1475305963,"classId":-1684552961,"package":"io.harness.dtos.deploymentinfo","class":"K8sDeploymentInfoDTO","method":"getNamespaces","params":"()"}}
{"test":{"id":1390315293,"classId":-206442501,"package":"io.harness.service.instancesynchandler","class":"K8sInstanceSyncHandlerTest","method":"testGetInstanceInfoForServerInstance","params":"()"},"source":{"id":1600489828,"classId":192269376,"package":"io.harness.k8s.model","class":"K8sContainer","method":"name","params":"(java.lang.String)"}}
{"test":{"id":724830717,"classId":-1497153642,"package":"io.harness","class":"CategoryTest"},"source":{"id":1867172510,"classId":991009712,"package":"io.harness.data.presentation","class":"ByteCountUtils","method":"humanReadableBin","params":"(long)"}}
{"test":{"id":1390315293,"classId":-206442501,"package":"io.harness.service.instancesynchandler","class":"K8sInstanceSyncHandlerTest","method":"testGetInstanceInfoForServerInstance","params":"()"},"source":{"id":1831475562,"classId":-1297480033,"package":"io.harness.dtos.instanceinfo","class":"K8sInstanceInfoDTO","method":"getNamespace","params":"()"}}
{"test":{"id":846275576,"classId":-206442501,"package":"io.harness.service.instancesynchandler","class":"K8sInstanceSyncHandlerTest","method":"testGetDeploymentInfo","params":"()"},"source":{"id":-1882221936,"classId":1909834988,"package":"io.harness.delegate.beans.instancesync.info","class":"K8sServerInstanceInfo","method":"getReleaseName","params":"()"}}
{"test":{"id":1390315293,"classId":-206442501,"package":"io.harness.service.instancesynchandler","class":"K8sInstanceSyncHandlerTest","method":"testGetInstanceInfoForServerInstance","params":"()"},"source":{"id":-1195413530,"classId":192269376,"package":"io.harness.k8s.model","class":"K8sContainer","method":"equals","params":"(java.lang.Object)"}}
{"test":{"id":1390315293,"classId":-206442501,"package":"io.harness.service.instancesynchandler","class":"K8sInstanceSyncHandlerTest","method":"testGetInstanceInfoForServerInstance","params":"()"},"source":{"id":-163147180,"classId":1909834988,"package":"io.harness.delegate.beans.instancesync.info","class":"K8sServerInstanceInfo","method":"","params":"()"}}
{"test":{"id":1305440404,"classId":-206442501,"package":"io.harness.service.instancesynchandler","class":"K8sInstanceSyncHandlerTest","method":"testGetInstanceType","params":"()"},"source":{"id":-1417727180,"classId":1536503721,"package":"io.harness.service.instancesynchandler","class":"K8sInstanceSyncHandler","method":"getInstanceType","params":"()"}}
{"test":{"id":1305440404,"classId":-206442501,"package":"io.harness.service.instancesynchandler","class":"K8sInstanceSyncHandlerTest","method":"testGetInstanceType","params":"()"},"source":{"id":-1326709448,"classId":1132516344,"package":"io.harness.entities","class":"InstanceType","method":"","params":"(java.lang.String,int)"}}
{"test":{"id":846275576,"classId":-206442501,"package":"io.harness.service.instancesynchandler","class":"K8sInstanceSyncHandlerTest","method":"testGetDeploymentInfo","params":"()"},"source":{"id":-486391412,"classId":-1684552961,"package":"io.harness.dtos.deploymentinfo","class":"K8sDeploymentInfoDTO","method":"releaseName","params":"(java.lang.String)"}}
{"test":{"id":846275576,"classId":-206442501,"package":"io.harness.service.instancesynchandler","class":"K8sInstanceSyncHandlerTest","method":"testGetDeploymentInfo","params":"()"},"source":{"id":-1186970759,"classId":1909834988,"package":"io.harness.delegate.beans.instancesync.info","class":"K8sServerInstanceInfo","method":"releaseName","params":"(java.lang.String)"}}
{"test":{"id":846275576,"classId":-206442501,"package":"io.harness.service.instancesynchandler","class":"K8sInstanceSyncHandlerTest","method":"testGetDeploymentInfo","params":"()"},"source":{"id":756226668,"classId":-1644404251,"package":"io.harness.data.structure","class":"EmptyPredicate","method":"isEmpty","params":"(java.util.Collection)"}}
{"test":{"id":1390315293,"classId":-206442501,"package":"io.harness.service.instancesynchandler","class":"K8sInstanceSyncHandlerTest","method":"testGetInstanceInfoForServerInstance","params":"()"},"source":{"id":-2111371199,"classId":192269376,"package":"io.harness.k8s.model","class":"K8sContainer","method":"builder","params":"()"}}
{"test":{"id":1390315293,"classId":-206442501,"package":"io.harness.service.instancesynchandler","class":"K8sInstanceSyncHandlerTest","method":"testGetInstanceInfoForServerInstance","params":"()"},"source":{"id":296216065,"classId":-1297480033,"package":"io.harness.dtos.instanceinfo","class":"K8sInstanceInfoDTO","method":"getPodName","params":"()"}}
{"test":{"id":846275576,"classId":-206442501,"package":"io.harness.service.instancesynchandler","class":"K8sInstanceSyncHandlerTest","method":"testGetDeploymentInfo","params":"()"},"source":{"id":1309449572,"classId":1909834988,"package":"io.harness.delegate.beans.instancesync.info","class":"K8sServerInstanceInfo","method":"getBlueGreenColor","params":"()"}}
{"test":{"id":1390315293,"classId":-206442501,"package":"io.harness.service.instancesynchandler","class":"K8sInstanceSyncHandlerTest","method":"testGetInstanceInfoForServerInstance","params":"()"},"source":{"id":-253831166,"classId":1909834988,"package":"io.harness.delegate.beans.instancesync.info","class":"K8sServerInstanceInfo","method":"build","params":"()"}}
{"test":{"id":846275576,"classId":-206442501,"package":"io.harness.service.instancesynchandler","class":"K8sInstanceSyncHandlerTest","method":"testGetDeploymentInfo","params":"()"},"source":{"id":537432167,"classId":-1684552961,"package":"io.harness.dtos.deploymentinfo","class":"K8sDeploymentInfoDTO","method":"","params":"()"}}
{"test":{"id":846275576,"classId":-206442501,"package":"io.harness.service.instancesynchandler","class":"K8sInstanceSyncHandlerTest","method":"testGetDeploymentInfo","params":"()"},"source":{"id":-1132906288,"classId":2127855401,"package":"io.harness.cdng.infra.beans","class":"K8sDirectInfrastructureOutcome","method":"","params":"(java.lang.String,java.lang.String,java.lang.String,io.harness.steps.environment.EnvironmentOutcome,java.lang.String)"}}
{"test":{"id":1390315293,"classId":-206442501,"package":"io.harness.service.instancesynchandler","class":"K8sInstanceSyncHandlerTest","method":"testGetInstanceInfoForServerInstance","params":"()"},"source":{"id":-794569661,"classId":-1297480033,"package":"io.harness.dtos.instanceinfo","class":"K8sInstanceInfoDTO","method":"getReleaseName","params":"()"}}
{"test":{"id":1390315293,"classId":-206442501,"package":"io.harness.service.instancesynchandler","class":"K8sInstanceSyncHandlerTest","method":"testGetInstanceInfoForServerInstance","params":"()"},"source":{"id":205702817,"classId":1909834988,"package":"io.harness.delegate.beans.instancesync.info","class":"K8sServerInstanceInfo","method":"blueGreenColor","params":"(java.lang.String)"}}
{"test":{"id":1390315293,"classId":-206442501,"package":"io.harness.service.instancesynchandler","class":"K8sInstanceSyncHandlerTest","method":"testGetInstanceInfoForServerInstance","params":"()"},"source":{"id":-1880712792,"classId":192269376,"package":"io.harness.k8s.model","class":"K8sContainer","method":"","params":"()"}}
{"test":{"id":846275576,"classId":-206442501,"package":"io.harness.service.instancesynchandler","class":"K8sInstanceSyncHandlerTest","method":"testGetDeploymentInfo","params":"()"},"source":{"id":306773760,"classId":-1684552961,"package":"io.harness.dtos.deploymentinfo","class":"K8sDeploymentInfoDTO","method":"builder","params":"()"}}
